Metadata-Version: 2.1
Name: TTS2
Version: 0.7.0
Summary: Deep learning for Text to Speech by Coqui.
Home-page: https://github.com/coqui-ai/TTS
Author: Eren Gölge
Author-email: egolge@coqui.ai
License: MPL-2.0
Project-URL: Documentation, https://github.com/coqui-ai/TTS/wiki
Project-URL: Tracker, https://github.com/coqui-ai/TTS/issues
Project-URL: Repository, https://github.com/coqui-ai/TTS
Project-URL: Discussions, https://github.com/coqui-ai/TTS/discussions
Platform: UNKNOWN
Classifier: Programming Language :: Python
Classifier: Programming Language :: Python :: 3
Classifier: Programming Language :: Python :: 3.7
Classifier: Programming Language :: Python :: 3.8
Classifier: Programming Language :: Python :: 3.9
Classifier: Programming Language :: Python :: 3.10
Classifier: Development Status :: 3 - Alpha
Classifier: Intended Audience :: Science/Research
Classifier: Intended Audience :: Developers
Classifier: Operating System :: POSIX :: Linux
Classifier: License :: OSI Approved :: Mozilla Public License 2.0 (MPL 2.0)
Classifier: Topic :: Software Development
Classifier: Topic :: Software Development :: Libraries :: Python Modules
Classifier: Topic :: Multimedia :: Sound/Audio :: Speech
Classifier: Topic :: Multimedia :: Sound/Audio
Classifier: Topic :: Multimedia
Classifier: Topic :: Scientific/Engineering :: Artificial Intelligence
Requires-Python: >=3.7.0, <3.11
License-File: LICENSE.txt
Requires-Dist: numpy
Requires-Dist: cython (==0.29.28)
Requires-Dist: scipy (>=1.4.0)
Requires-Dist: torch (>=1.7)
Requires-Dist: torchaudio
Requires-Dist: soundfile
Requires-Dist: librosa (==0.8.0)
Requires-Dist: numba (==0.53.1)
Requires-Dist: inflect
Requires-Dist: tqdm
Requires-Dist: anyascii
Requires-Dist: pyyaml
Requires-Dist: fsspec (>=2021.04.0)
Requires-Dist: flask
Requires-Dist: pysbd
Requires-Dist: umap-learn (==0.5.1)
Requires-Dist: pandas
Requires-Dist: matplotlib
Requires-Dist: pyworld (==0.2.10)
Requires-Dist: trainer
Requires-Dist: coqpit (>=0.0.16)
Requires-Dist: jieba
Requires-Dist: pypinyin
Requires-Dist: mecab-python3 (==1.0.5)
Requires-Dist: unidic-lite (==1.0.8)
Requires-Dist: gruut[cs,de,es,fr,it,nl,pt,ru,sv] (==2.2.3)
Provides-Extra: all
Requires-Dist: black ; extra == 'all'
Requires-Dist: coverage ; extra == 'all'
Requires-Dist: isort ; extra == 'all'
Requires-Dist: nose2 ; extra == 'all'
Requires-Dist: pylint (==2.10.2) ; extra == 'all'
Requires-Dist: bokeh (==1.4.0) ; extra == 'all'
Provides-Extra: dev
Requires-Dist: black ; extra == 'dev'
Requires-Dist: coverage ; extra == 'dev'
Requires-Dist: isort ; extra == 'dev'
Requires-Dist: nose2 ; extra == 'dev'
Requires-Dist: pylint (==2.10.2) ; extra == 'dev'
Provides-Extra: notebooks
Requires-Dist: bokeh (==1.4.0) ; extra == 'notebooks'
